Workbook

Sheet Supuestos
A1: Concepto | B1: Valor
A2: Clientes Año 1 | B2: 50
A3: Crecimiento anual | B3: 0.4
A4: Ticket consultoría | B4: 2000
A5: Suscripción mensual | B5: 50
A6: Success fee % | B6: 0.04
A7: Monto financiamiento promedio | B7: 50000
A8: Costos fijos anuales | B8: 180000
A9: Costos variables % | B9: 0.2
A10: Tasa descuento | B10: 0.15

Sheet Proyecciones
A1: Año | B1: Clientes | C1: Ingresos Consultoría | D1: Ingresos Suscripción | E1: Success Fee | F1: Ingresos Totales | G1: Costos Variables | H1: Costos Fijos | I1: Flujo Neto
A2: 1 | B2: =Supuestos!B2 | C2: =B2*Supuestos!B4 | D2: =B2*Supuestos!B5*12 | E2: =B2*Supuestos!B6*Supuestos!B7 | F2: =SUM(C2:E2) | G2: =F2*Supuestos!B9 | H2: =Supuestos!B8 | I2: =F2-G2-H2
A3: 2 | B3: =B2*(1+Supuestos!B3) | C3: =B3*Supuestos!B4 | D3: =B3*Supuestos!B5*12 | E3: =B3*Supuestos!B6*Supuestos!B7 | F3: =SUM(C3:E3) | G3: =F3*Supuestos!B9 | H3: =Supuestos!B8 | I3: =F3-G3-H3
A4: 3 | B4: =B3*(1+Supuestos!B3) | C4: =B4*Supuestos!B4 | D4: =B4*Supuestos!B5*12 | E4: =B4*Supuestos!B6*Supuestos!B7 | F4: =SUM(C4:E4) | G4: =F4*Supuestos!B9 | H4: =Supuestos!B8 | I4: =F4-G4-H4
A5: 4 | B5: =B4*(1+Supuestos!B3) | C5: =B5*Supuestos!B4 | D5: =B5*Supuestos!B5*12 | E5: =B5*Supuestos!B6*Supuestos!B7 | F5: =SUM(C5:E5) | G5: =F5*Supuestos!B9 | H5: =Supuestos!B8 | I5: =F5-G5-H5
A6: 5 | B6: =B5*(1+Supuestos!B3) | C6: =B6*Supuestos!B4 | D6: =B6*Supuestos!B5*12 | E6: =B6*Supuestos!B6*Supuestos!B7 | F6: =SUM(C6:E6) | G6: =F6*Supuestos!B9 | H6: =Supuestos!B8 | I6: =F6-G6-H6

Sheet VAN_TIR
A1: Flujos
A2: -50000 | C2: VAN | D2: TIR
A3: =Proyecciones!I2 | C3: =NPV(Supuestos!B10,A3:A7)+A2 | D3: =IRR(A2:A7)
A4: =Proyecciones!I3
A5: =Proyecciones!I4
A6: =Proyecciones!I5
A7: =Proyecciones!I6
